{"inkVersion":20,"root":[["^Looking for something? ",{"#":"speaker:Bartender"},{"#":"portrait:NPCNetral"},{"#":"layout:leftBar"},"\n",{"->":"main"},["done",{"#f":5,"#n":"g-0"}],null],"done",{"main":[["^Looking for something?","\n","ev","str","^Shop","/str","/ev",{"*":".^.c-0","flg":4},"ev","str","^Guide","/str","/ev",{"*":".^.c-1","flg":4},{"c-0":["\n","^You should buy this weapon to overcome the next level. This is the only weapon that available right now ",{"#":"portrait:NPCNetral"},"\n",{"->":".^.^.g-0"},{"#f":5}],"c-1":["\n","^When you entering Slum area, you should be careful with the gang ",{"#":"portrait:NPCNetral"},"\n",{"->":".^.^.g-0"},{"#f":5}],"g-0":["^Well, do you have any more questions? ",{"#":"speaker:Bartender"},{"#":"portrait:NPCHappy"},{"#":"layout:left1"},"\n","ev","str","^Yes","/str","/ev",{"*":".^.c-2","flg":4},"ev","str","^No","/str","/ev",{"*":".^.c-3","flg":4},{"c-2":["\n",{"->":"main"},{"#f":5}],"c-3":["\n","^Goodbye then!","\n","end",{"#f":5}],"#f":5}]}],{"#f":1}],"#f":1}],"listDefs":{}}